[
    {
        "title": "Definitely Not Fried Chicken",
        "id": "b916500f733b4973802bdb4fdb276515",
        "description": "Definitely Not Fried Chicken is a business management sim with a Twist! Grow your drugs trade through legitimate fronts, managing both sides of the business. Acquire new \"businesses\", meet new clientele, Develop more potent narcotics, make lots of money and leave a city in ruin!",
        "original_price_fmt": "‏11.59 US$",
        "discount_price_fmt": "0",
        "currency": "USD",
        "expiry_date": null
    }
]